[
  {
    "sha": "9d0d16b03e1bf60929f1c5ff29306cde3a80d8ee",
    "filename": "pom.xml",
    "status": "modified",
    "additions": 3,
    "deletions": 3,
    "changes": 6,
    "blob_url": "https://github.com/sardell/metron/blob/ef2407b1acfdd8e10e6391151f84a444bf2b53b8/pom.xml",
    "raw_url": "https://github.com/sardell/metron/raw/ef2407b1acfdd8e10e6391151f84a444bf2b53b8/pom.xml",
    "contents_url": "https://api.github.com/repos/sardell/metron/contents/pom.xml?ref=ef2407b1acfdd8e10e6391151f84a444bf2b53b8",
    "patch": "@@ -91,7 +91,7 @@\n         <base_flux_version>1.0.1</base_flux_version>\n         <base_kafka_version>0.10.0</base_kafka_version>\n         <base_hadoop_version>2.7.1</base_hadoop_version>\n-        <base_hbase_version>1.1.1</base_hbase_version>\n+        <base_hbase_version>2.4.0</base_hbase_version>\n         <base_flume_version>1.5.2</base_flume_version>\n         <!-- full dependency versions -->\n         <global_accumulo_version>1.8.0</global_accumulo_version>\n@@ -137,7 +137,7 @@\n         <global_httpclient_version>4.3.2</global_httpclient_version>\n         <global_aesh_version>0.66.19</global_aesh_version>\n         <global_jacoco_version>0.8.3</global_jacoco_version>\n-        <argLine></argLine>\n+        <argLine/>\n     </properties>\n \n     <profiles>\n@@ -282,7 +282,7 @@\n                 <artifactId>cobertura-maven-plugin</artifactId>\n                 <version>2.7</version>\n                 <configuration>\n-                    <check />\n+                    <check/>\n                     <formats>\n                         <format>html</format>\n                     </formats>"
  }
]
