[
  {
    "sha": "bea3b25eaf6532bfd29407f7f269976251641601",
    "filename": ".gitignore",
    "status": "modified",
    "additions": 10,
    "deletions": 2,
    "changes": 12,
    "blob_url": "https://github.com/krettt/KretOleg/blob/681451ce8bc7845de180e20b631464b9e9cdbdaa/.gitignore",
    "raw_url": "https://github.com/krettt/KretOleg/raw/681451ce8bc7845de180e20b631464b9e9cdbdaa/.gitignore",
    "contents_url": "https://api.github.com/repos/krettt/KretOleg/contents/.gitignore?ref=681451ce8bc7845de180e20b631464b9e9cdbdaa",
    "patch": "@@ -10,6 +10,16 @@\n # Mobile Tools for Java (J2ME)\n .mtj.tmp/\n \n+# IntellijIdea files\n+/.idea\n+\n+#Alure\n+allure-results/*\n+allure-report/*\n+\n+#Target\n+target/*\n+\n # Package Files #\n *.jar\n *.war\n@@ -19,5 +29,3 @@\n *.tar.gz\n *.rar\n \n-# virtual machine crash logs, see http://www.java.com/en/download/help/error_hotspot.xml\n-hs_err_pid*"
  },
  {
    "sha": "26d33521af10bcc7fd8cea344038eaaeb78d0ef5",
    "filename": ".idea/.gitignore",
    "status": "removed",
    "additions": 0,
    "deletions": 3,
    "changes": 3,
    "blob_url": "https://github.com/krettt/KretOleg/blob/fcd4fdc642d52320a4e3f84e4b15a35a9d3def65/.idea/.gitignore",
    "raw_url": "https://github.com/krettt/KretOleg/raw/fcd4fdc642d52320a4e3f84e4b15a35a9d3def65/.idea/.gitignore",
    "contents_url": "https://api.github.com/repos/krettt/KretOleg/contents/.idea/.gitignore?ref=fcd4fdc642d52320a4e3f84e4b15a35a9d3def65",
    "patch": "@@ -1,3 +0,0 @@\n-# Default ignored files\n-/shelf/\n-/workspace.xml"
  },
  {
    "sha": "91063aa21119ce3a01ff083d564fc9ebcd1fa1e9",
    "filename": ".idea/misc.xml",
    "status": "removed",
    "additions": 0,
    "deletions": 6,
    "changes": 6,
    "blob_url": "https://github.com/krettt/KretOleg/blob/fcd4fdc642d52320a4e3f84e4b15a35a9d3def65/.idea/misc.xml",
    "raw_url": "https://github.com/krettt/KretOleg/raw/fcd4fdc642d52320a4e3f84e4b15a35a9d3def65/.idea/misc.xml",
    "contents_url": "https://api.github.com/repos/krettt/KretOleg/contents/.idea/misc.xml?ref=fcd4fdc642d52320a4e3f84e4b15a35a9d3def65",
    "patch": "@@ -1,6 +0,0 @@\n-<?xml version=\"1.0\" encoding=\"UTF-8\"?>\n-<project version=\"4\">\n-  <component name=\"ProjectRootManager\" version=\"2\" languageLevel=\"JDK_15\" default=\"true\" project-jdk-name=\"15\" project-jdk-type=\"JavaSDK\">\n-    <output url=\"file://$PROJECT_DIR$/out\" />\n-  </component>\n-</project>\n\\ No newline at end of file"
  },
  {
    "sha": "0c715da3c65b9f6c5850bf7d2b4bf43398c17418",
    "filename": ".idea/modules.xml",
    "status": "removed",
    "additions": 0,
    "deletions": 8,
    "changes": 8,
    "blob_url": "https://github.com/krettt/KretOleg/blob/fcd4fdc642d52320a4e3f84e4b15a35a9d3def65/.idea/modules.xml",
    "raw_url": "https://github.com/krettt/KretOleg/raw/fcd4fdc642d52320a4e3f84e4b15a35a9d3def65/.idea/modules.xml",
    "contents_url": "https://api.github.com/repos/krettt/KretOleg/contents/.idea/modules.xml?ref=fcd4fdc642d52320a4e3f84e4b15a35a9d3def65",
    "patch": "@@ -1,8 +0,0 @@\n-<?xml version=\"1.0\" encoding=\"UTF-8\"?>\n-<project version=\"4\">\n-  <component name=\"ProjectModuleManager\">\n-    <modules>\n-      <module fileurl=\"file://$PROJECT_DIR$/KretOleg.iml\" filepath=\"$PROJECT_DIR$/KretOleg.iml\" />\n-    </modules>\n-  </component>\n-</project>\n\\ No newline at end of file"
  },
  {
    "sha": "e96534fb27b68192f27f985d3879e173ec77adb8",
    "filename": ".idea/uiDesigner.xml",
    "status": "removed",
    "additions": 0,
    "deletions": 124,
    "changes": 124,
    "blob_url": "https://github.com/krettt/KretOleg/blob/fcd4fdc642d52320a4e3f84e4b15a35a9d3def65/.idea/uiDesigner.xml",
    "raw_url": "https://github.com/krettt/KretOleg/raw/fcd4fdc642d52320a4e3f84e4b15a35a9d3def65/.idea/uiDesigner.xml",
    "contents_url": "https://api.github.com/repos/krettt/KretOleg/contents/.idea/uiDesigner.xml?ref=fcd4fdc642d52320a4e3f84e4b15a35a9d3def65",
    "patch": "@@ -1,124 +0,0 @@\n-<?xml version=\"1.0\" encoding=\"UTF-8\"?>\n-<project version=\"4\">\n-  <component name=\"Palette2\">\n-    <group name=\"Swing\">\n-      <item class=\"com.intellij.uiDesigner.HSpacer\" tooltip-text=\"Horizontal Spacer\" icon=\"/com/intellij/uiDesigner/icons/hspacer.png\" removable=\"false\" auto-create-binding=\"false\" can-attach-label=\"false\">\n-        <default-constraints vsize-policy=\"1\" hsize-policy=\"6\" anchor=\"0\" fill=\"1\" />\n-      </item>\n-      <item class=\"com.intellij.uiDesigner.VSpacer\" tooltip-text=\"Vertical Spacer\" icon=\"/com/intellij/uiDesigner/icons/vspacer.png\" removable=\"false\" auto-create-binding=\"false\" can-attach-label=\"false\">\n-        <default-constraints vsize-policy=\"6\" hsize-policy=\"1\" anchor=\"0\" fill=\"2\" />\n-      </item>\n-      <item class=\"javax.swing.JPanel\" icon=\"/com/intellij/uiDesigner/icons/panel.png\" removable=\"false\" auto-create-binding=\"false\" can-attach-label=\"false\">\n-        <default-constraints vsize-policy=\"3\" hsize-policy=\"3\" anchor=\"0\" fill=\"3\" />\n-      </item>\n-      <item class=\"javax.swing.JScrollPane\" icon=\"/com/intellij/uiDesigner/icons/scrollPane.png\" removable=\"false\" auto-create-binding=\"false\" can-attach-label=\"true\">\n-        <default-constraints vsize-policy=\"7\" hsize-policy=\"7\" anchor=\"0\" fill=\"3\" />\n-      </item>\n-      <item class=\"javax.swing.JButton\" icon=\"/com/intellij/uiDesigner/icons/button.png\" removable=\"false\" auto-create-binding=\"true\" can-attach-label=\"false\">\n-        <default-constraints vsize-policy=\"0\" hsize-policy=\"3\" anchor=\"0\" fill=\"1\" />\n-        <initial-values>\n-          <property name=\"text\" value=\"Button\" />\n-        </initial-values>\n-      </item>\n-      <item class=\"javax.swing.JRadioButton\" icon=\"/com/intellij/uiDesigner/icons/radioButton.png\" removable=\"false\" auto-create-binding=\"true\" can-attach-label=\"false\">\n-        <default-constraints vsize-policy=\"0\" hsize-policy=\"3\" anchor=\"8\" fill=\"0\" />\n-        <initial-values>\n-          <property name=\"text\" value=\"RadioButton\" />\n-        </initial-values>\n-      </item>\n-      <item class=\"javax.swing.JCheckBox\" icon=\"/com/intellij/uiDesigner/icons/checkBox.png\" removable=\"false\" auto-create-binding=\"true\" can-attach-label=\"false\">\n-        <default-constraints vsize-policy=\"0\" hsize-policy=\"3\" anchor=\"8\" fill=\"0\" />\n-        <initial-values>\n-          <property name=\"text\" value=\"CheckBox\" />\n-        </initial-values>\n-      </item>\n-      <item class=\"javax.swing.JLabel\" icon=\"/com/intellij/uiDesigner/icons/label.png\" removable=\"false\" auto-create-binding=\"false\" can-attach-label=\"false\">\n-        <default-constraints vsize-policy=\"0\" hsize-policy=\"0\" anchor=\"8\" fill=\"0\" />\n-        <initial-values>\n-          <property name=\"text\" value=\"Label\" />\n-        </initial-values>\n-      </item>\n-      <item class=\"javax.swing.JTextField\" icon=\"/com/intellij/uiDesigner/icons/textField.png\" removable=\"false\" auto-create-binding=\"true\" can-attach-label=\"true\">\n-        <default-constraints vsize-policy=\"0\" hsize-policy=\"6\" anchor=\"8\" fill=\"1\">\n-          <preferred-size width=\"150\" height=\"-1\" />\n-        </default-constraints>\n-      </item>\n-      <item class=\"javax.swing.JPasswordField\" icon=\"/com/intellij/uiDesigner/icons/passwordField.png\" removable=\"false\" auto-create-binding=\"true\" can-attach-label=\"true\">\n-        <default-constraints vsize-policy=\"0\" hsize-policy=\"6\" anchor=\"8\" fill=\"1\">\n-          <preferred-size width=\"150\" height=\"-1\" />\n-        </default-constraints>\n-      </item>\n-      <item class=\"javax.swing.JFormattedTextField\" icon=\"/com/intellij/uiDesigner/icons/formattedTextField.png\" removable=\"false\" auto-create-binding=\"true\" can-attach-label=\"true\">\n-        <default-constraints vsize-policy=\"0\" hsize-policy=\"6\" anchor=\"8\" fill=\"1\">\n-          <preferred-size width=\"150\" height=\"-1\" />\n-        </default-constraints>\n-      </item>\n-      <item class=\"javax.swing.JTextArea\" icon=\"/com/intellij/uiDesigner/icons/textArea.png\" removable=\"false\" auto-create-binding=\"true\" can-attach-label=\"true\">\n-        <default-constraints vsize-policy=\"6\" hsize-policy=\"6\" anchor=\"0\" fill=\"3\">\n-          <preferred-size width=\"150\" height=\"50\" />\n-        </default-constraints>\n-      </item>\n-      <item class=\"javax.swing.JTextPane\" icon=\"/com/intellij/uiDesigner/icons/textPane.png\" removable=\"false\" auto-create-binding=\"true\" can-attach-label=\"true\">\n-        <default-constraints vsize-policy=\"6\" hsize-policy=\"6\" anchor=\"0\" fill=\"3\">\n-          <preferred-size width=\"150\" height=\"50\" />\n-        </default-constraints>\n-      </item>\n-      <item class=\"javax.swing.JEditorPane\" icon=\"/com/intellij/uiDesigner/icons/editorPane.png\" removable=\"false\" auto-create-binding=\"true\" can-attach-label=\"true\">\n-        <default-constraints vsize-policy=\"6\" hsize-policy=\"6\" anchor=\"0\" fill=\"3\">\n-          <preferred-size width=\"150\" height=\"50\" />\n-        </default-constraints>\n-      </item>\n-      <item class=\"javax.swing.JComboBox\" icon=\"/com/intellij/uiDesigner/icons/comboBox.png\" removable=\"false\" auto-create-binding=\"true\" can-attach-label=\"true\">\n-        <default-constraints vsize-policy=\"0\" hsize-policy=\"2\" anchor=\"8\" fill=\"1\" />\n-      </item>\n-      <item class=\"javax.swing.JTable\" icon=\"/com/intellij/uiDesigner/icons/table.png\" removable=\"false\" auto-create-binding=\"true\" can-attach-label=\"false\">\n-        <default-constraints vsize-policy=\"6\" hsize-policy=\"6\" anchor=\"0\" fill=\"3\">\n-          <preferred-size width=\"150\" height=\"50\" />\n-        </default-constraints>\n-      </item>\n-      <item class=\"javax.swing.JList\" icon=\"/com/intellij/uiDesigner/icons/list.png\" removable=\"false\" auto-create-binding=\"true\" can-attach-label=\"false\">\n-        <default-constraints vsize-policy=\"6\" hsize-policy=\"2\" anchor=\"0\" fill=\"3\">\n-          <preferred-size width=\"150\" height=\"50\" />\n-        </default-constraints>\n-      </item>\n-      <item class=\"javax.swing.JTree\" icon=\"/com/intellij/uiDesigner/icons/tree.png\" removable=\"false\" auto-create-binding=\"true\" can-attach-label=\"false\">\n-        <default-constraints vsize-policy=\"6\" hsize-policy=\"6\" anchor=\"0\" fill=\"3\">\n-          <preferred-size width=\"150\" height=\"50\" />\n-        </default-constraints>\n-      </item>\n-      <item class=\"javax.swing.JTabbedPane\" icon=\"/com/intellij/uiDesigner/icons/tabbedPane.png\" removable=\"false\" auto-create-binding=\"true\" can-attach-label=\"false\">\n-        <default-constraints vsize-policy=\"3\" hsize-policy=\"3\" anchor=\"0\" fill=\"3\">\n-          <preferred-size width=\"200\" height=\"200\" />\n-        </default-constraints>\n-      </item>\n-      <item class=\"javax.swing.JSplitPane\" icon=\"/com/intellij/uiDesigner/icons/splitPane.png\" removable=\"false\" auto-create-binding=\"false\" can-attach-label=\"false\">\n-        <default-constraints vsize-policy=\"3\" hsize-policy=\"3\" anchor=\"0\" fill=\"3\">\n-          <preferred-size width=\"200\" height=\"200\" />\n-        </default-constraints>\n-      </item>\n-      <item class=\"javax.swing.JSpinner\" icon=\"/com/intellij/uiDesigner/icons/spinner.png\" removable=\"false\" auto-create-binding=\"true\" can-attach-label=\"true\">\n-        <default-constraints vsize-policy=\"0\" hsize-policy=\"6\" anchor=\"8\" fill=\"1\" />\n-      </item>\n-      <item class=\"javax.swing.JSlider\" icon=\"/com/intellij/uiDesigner/icons/slider.png\" removable=\"false\" auto-create-binding=\"true\" can-attach-label=\"false\">\n-        <default-constraints vsize-policy=\"0\" hsize-policy=\"6\" anchor=\"8\" fill=\"1\" />\n-      </item>\n-      <item class=\"javax.swing.JSeparator\" icon=\"/com/intellij/uiDesigner/icons/separator.png\" removable=\"false\" auto-create-binding=\"false\" can-attach-label=\"false\">\n-        <default-constraints vsize-policy=\"6\" hsize-policy=\"6\" anchor=\"0\" fill=\"3\" />\n-      </item>\n-      <item class=\"javax.swing.JProgressBar\" icon=\"/com/intellij/uiDesigner/icons/progressbar.png\" removable=\"false\" auto-create-binding=\"true\" can-attach-label=\"false\">\n-        <default-constraints vsize-policy=\"0\" hsize-policy=\"6\" anchor=\"0\" fill=\"1\" />\n-      </item>\n-      <item class=\"javax.swing.JToolBar\" icon=\"/com/intellij/uiDesigner/icons/toolbar.png\" removable=\"false\" auto-create-binding=\"false\" can-attach-label=\"false\">\n-        <default-constraints vsize-policy=\"0\" hsize-policy=\"6\" anchor=\"0\" fill=\"1\">\n-          <preferred-size width=\"-1\" height=\"20\" />\n-        </default-constraints>\n-      </item>\n-      <item class=\"javax.swing.JToolBar$Separator\" icon=\"/com/intellij/uiDesigner/icons/toolbarSeparator.png\" removable=\"false\" auto-create-binding=\"false\" can-attach-label=\"false\">\n-        <default-constraints vsize-policy=\"0\" hsize-policy=\"0\" anchor=\"0\" fill=\"1\" />\n-      </item>\n-      <item class=\"javax.swing.JScrollBar\" icon=\"/com/intellij/uiDesigner/icons/scrollbar.png\" removable=\"false\" auto-create-binding=\"true\" can-attach-label=\"false\">\n-        <default-constraints vsize-policy=\"6\" hsize-policy=\"0\" anchor=\"0\" fill=\"2\" />\n-      </item>\n-    </group>\n-  </component>\n-</project>\n\\ No newline at end of file"
  },
  {
    "sha": "35eb1ddfbbc029bcab630581847471d7f238ec53",
    "filename": ".idea/vcs.xml",
    "status": "removed",
    "additions": 0,
    "deletions": 6,
    "changes": 6,
    "blob_url": "https://github.com/krettt/KretOleg/blob/fcd4fdc642d52320a4e3f84e4b15a35a9d3def65/.idea/vcs.xml",
    "raw_url": "https://github.com/krettt/KretOleg/raw/fcd4fdc642d52320a4e3f84e4b15a35a9d3def65/.idea/vcs.xml",
    "contents_url": "https://api.github.com/repos/krettt/KretOleg/contents/.idea/vcs.xml?ref=fcd4fdc642d52320a4e3f84e4b15a35a9d3def65",
    "patch": "@@ -1,6 +0,0 @@\n-<?xml version=\"1.0\" encoding=\"UTF-8\"?>\n-<project version=\"4\">\n-  <component name=\"VcsDirectoryMappings\">\n-    <mapping directory=\"\" vcs=\"Git\" />\n-  </component>\n-</project>\n\\ No newline at end of file"
  },
  {
    "sha": "620448ec5e9c03b519899501b5a1d293add44809",
    "filename": ".idea/workspace.xml",
    "status": "removed",
    "additions": 0,
    "deletions": 135,
    "changes": 135,
    "blob_url": "https://github.com/krettt/KretOleg/blob/fcd4fdc642d52320a4e3f84e4b15a35a9d3def65/.idea/workspace.xml",
    "raw_url": "https://github.com/krettt/KretOleg/raw/fcd4fdc642d52320a4e3f84e4b15a35a9d3def65/.idea/workspace.xml",
    "contents_url": "https://api.github.com/repos/krettt/KretOleg/contents/.idea/workspace.xml?ref=fcd4fdc642d52320a4e3f84e4b15a35a9d3def65",
    "patch": "@@ -1,135 +0,0 @@\n-<?xml version=\"1.0\" encoding=\"UTF-8\"?>\n-<project version=\"4\">\n-  <component name=\"ChangeListManager\">\n-    <list default=\"true\" id=\"8cde360c-3e36-4d39-8c68-e7bb9d2c43f4\" name=\"Default Changelist\" comment=\"Lesson3.OOP\">\n-      <change afterPath=\"$PROJECT_DIR$/src/main/java/lesson3hotel/pageOfApp/SortedType.java\" afterDir=\"false\" />\n-      <change beforePath=\"$PROJECT_DIR$/.idea/workspace.xml\" beforeDir=\"false\" afterPath=\"$PROJECT_DIR$/.idea/workspace.xml\" afterDir=\"false\" />\n-      <change beforePath=\"$PROJECT_DIR$/src/main/java/lesson3hotel/DataSource.java\" beforeDir=\"false\" afterPath=\"$PROJECT_DIR$/src/main/java/lesson3hotel/DataSource.java\" afterDir=\"false\" />\n-      <change beforePath=\"$PROJECT_DIR$/src/main/java/lesson3hotel/InterfaceOfApp.java\" beforeDir=\"false\" afterPath=\"$PROJECT_DIR$/src/main/java/lesson3hotel/InterfaceOfApp.java\" afterDir=\"false\" />\n-      <change beforePath=\"$PROJECT_DIR$/src/main/java/lesson3hotel/hotel/room/Room.java\" beforeDir=\"false\" afterPath=\"$PROJECT_DIR$/src/main/java/lesson3hotel/hotel/room/Room.java\" afterDir=\"false\" />\n-      <change beforePath=\"$PROJECT_DIR$/src/main/java/lesson3hotel/hotel/room/TypeOfRoom.java\" beforeDir=\"false\" afterPath=\"$PROJECT_DIR$/src/main/java/lesson3hotel/hotel/room/TypeOfRoom.java\" afterDir=\"false\" />\n-      <change beforePath=\"$PROJECT_DIR$/src/main/java/lesson3hotel/pageOfApp/Booking.java\" beforeDir=\"false\" afterPath=\"$PROJECT_DIR$/src/main/java/lesson3hotel/pageOfApp/Booking.java\" afterDir=\"false\" />\n-      <change beforePath=\"$PROJECT_DIR$/src/main/java/lesson3hotel/pageOfApp/Registration.java\" beforeDir=\"false\" afterPath=\"$PROJECT_DIR$/src/main/java/lesson3hotel/pageOfApp/Registration.java\" afterDir=\"false\" />\n-      <change beforePath=\"$PROJECT_DIR$/src/main/java/lesson3hotel/users/AdminOfApp.java\" beforeDir=\"false\" afterPath=\"$PROJECT_DIR$/src/main/java/lesson3hotel/users/AdminOfApp.java\" afterDir=\"false\" />\n-      <change beforePath=\"$PROJECT_DIR$/src/main/java/lesson3hotel/users/Manager.java\" beforeDir=\"false\" afterPath=\"$PROJECT_DIR$/src/main/java/lesson3hotel/users/Manager.java\" afterDir=\"false\" />\n-    </list>\n-    <option name=\"SHOW_DIALOG\" value=\"false\" />\n-    <option name=\"HIGHLIGHT_CONFLICTS\" value=\"true\" />\n-    <option name=\"HIGHLIGHT_NON_ACTIVE_CHANGELIST\" value=\"false\" />\n-    <option name=\"LAST_RESOLUTION\" value=\"IGNORE\" />\n-  </component>\n-  <component name=\"FileTemplateManagerImpl\">\n-    <option name=\"RECENT_TEMPLATES\">\n-      <list>\n-        <option value=\"Interface\" />\n-        <option value=\"Class\" />\n-        <option value=\"Enum\" />\n-      </list>\n-    </option>\n-  </component>\n-  <component name=\"Git.Settings\">\n-    <option name=\"RECENT_BRANCH_BY_REPOSITORY\">\n-      <map>\n-        <entry key=\"$PROJECT_DIR$\" value=\"lesson3\" />\n-      </map>\n-    </option>\n-    <option name=\"RECENT_GIT_ROOT_PATH\" value=\"$PROJECT_DIR$\" />\n-  </component>\n-  <component name=\"ProjectId\" id=\"1nsHVu1So5h7hozkzUNmtMZXNmN\" />\n-  <component name=\"ProjectViewState\">\n-    <option name=\"hideEmptyMiddlePackages\" value=\"true\" />\n-    <option name=\"showLibraryContents\" value=\"true\" />\n-  </component>\n-  <component name=\"PropertiesComponent\">\n-    <property name=\"RunOnceActivity.OpenProjectViewOnStart\" value=\"true\" />\n-    <property name=\"RunOnceActivity.ShowReadmeOnStart\" value=\"true\" />\n-    <property name=\"SHARE_PROJECT_CONFIGURATION_FILES\" value=\"true\" />\n-    <property name=\"last_opened_file_path\" value=\"$PROJECT_DIR$\" />\n-    <property name=\"project.structure.last.edited\" value=\"Modules\" />\n-    <property name=\"project.structure.proportion\" value=\"0.0\" />\n-    <property name=\"project.structure.side.proportion\" value=\"0.0\" />\n-    <property name=\"settings.editor.selected.configurable\" value=\"inlay.hints.JAVA\" />\n-  </component>\n-  <component name=\"RunManager\" selected=\"Application.InterfaceOfApp\">\n-    <configuration name=\"InterfaceOfApp\" type=\"Application\" factoryName=\"Application\" temporary=\"true\" nameIsGenerated=\"true\">\n-      <option name=\"MAIN_CLASS_NAME\" value=\"main.java.lesson3hotel.InterfaceOfApp\" />\n-      <module name=\"KretOleg\" />\n-      <extension name=\"coverage\">\n-        <pattern>\n-          <option name=\"PATTERN\" value=\"main.java.lesson3hotel.*\" />\n-          <option name=\"ENABLED\" value=\"true\" />\n-        </pattern>\n-      </extension>\n-      <method v=\"2\">\n-        <option name=\"Make\" enabled=\"true\" />\n-      </method>\n-    </configuration>\n-    <configuration name=\"lesson\" type=\"Application\" factoryName=\"Application\" temporary=\"true\" nameIsGenerated=\"true\">\n-      <option name=\"MAIN_CLASS_NAME\" value=\"lesson\" />\n-      <module name=\"KretOleg\" />\n-      <method v=\"2\">\n-        <option name=\"Make\" enabled=\"true\" />\n-      </method>\n-    </configuration>\n-    <configuration name=\"mainCheck\" type=\"Application\" factoryName=\"Application\" temporary=\"true\" nameIsGenerated=\"true\">\n-      <option name=\"MAIN_CLASS_NAME\" value=\"main.java.lesson2checkName.mainCheck\" />\n-      <module name=\"KretOleg\" />\n-      <extension name=\"coverage\">\n-        <pattern>\n-          <option name=\"PATTERN\" value=\"main.java.lesson2checkName.*\" />\n-          <option name=\"ENABLED\" value=\"true\" />\n-        </pattern>\n-      </extension>\n-      <method v=\"2\">\n-        <option name=\"Make\" enabled=\"true\" />\n-      </method>\n-    </configuration>\n-    <recent_temporary>\n-      <list>\n-        <item itemvalue=\"Application.InterfaceOfApp\" />\n-        <item itemvalue=\"Application.mainCheck\" />\n-        <item itemvalue=\"Application.lesson\" />\n-        <item itemvalue=\"Application.mainCheck\" />\n-        <item itemvalue=\"Application.lesson\" />\n-      </list>\n-    </recent_temporary>\n-  </component>\n-  <component name=\"SpellCheckerSettings\" RuntimeDictionaries=\"0\" Folders=\"0\" CustomDictionaries=\"0\" DefaultDictionary=\"application-level\" UseSingleDictionary=\"true\" transferred=\"true\" />\n-  <component name=\"TaskManager\">\n-    <task active=\"true\" id=\"Default\" summary=\"Default task\">\n-      <changelist id=\"8cde360c-3e36-4d39-8c68-e7bb9d2c43f4\" name=\"Default Changelist\" comment=\"\" />\n-      <created>1612171907511</created>\n-      <option name=\"number\" value=\"Default\" />\n-      <option name=\"presentableId\" value=\"Default\" />\n-      <updated>1612171907511</updated>\n-    </task>\n-    <servers />\n-  </component>\n-  <component name=\"Vcs.Log.Tabs.Properties\">\n-    <option name=\"TAB_STATES\">\n-      <map>\n-        <entry key=\"MAIN\">\n-          <value>\n-            <State />\n-          </value>\n-        </entry>\n-      </map>\n-    </option>\n-    <option name=\"oldMeFiltersMigrated\" value=\"true\" />\n-  </component>\n-  <component name=\"XDebuggerManager\">\n-    <breakpoint-manager>\n-      <breakpoints>\n-        <breakpoint enabled=\"true\" type=\"java-exception\">\n-          <properties class=\"java.lang.StackOverflowError\" package=\"java.lang\" />\n-          <option name=\"timeStamp\" value=\"2\" />\n-        </breakpoint>\n-      </breakpoints>\n-    </breakpoint-manager>\n-    <watches-manager>\n-      <configuration name=\"Application\">\n-        <watch expression=\"chosenHotel.getRooms(number,typeOfRoom);\" language=\"JAVA\" />\n-      </configuration>\n-    </watches-manager>\n-  </component>\n-</project>\n\\ No newline at end of file"
  },
  {
    "sha": "b08a1afdf394cb4f56cd86b3d67c4ecff9228c6f",
    "filename": "KretOleg.iml",
    "status": "modified",
    "additions": 87,
    "deletions": 4,
    "changes": 91,
    "blob_url": "https://github.com/krettt/KretOleg/blob/681451ce8bc7845de180e20b631464b9e9cdbdaa/KretOleg.iml",
    "raw_url": "https://github.com/krettt/KretOleg/raw/681451ce8bc7845de180e20b631464b9e9cdbdaa/KretOleg.iml",
    "contents_url": "https://api.github.com/repos/krettt/KretOleg/contents/KretOleg.iml?ref=681451ce8bc7845de180e20b631464b9e9cdbdaa",
    "patch": "@@ -1,11 +1,94 @@\n <?xml version=\"1.0\" encoding=\"UTF-8\"?>\n-<module type=\"JAVA_MODULE\" version=\"4\">\n-  <component name=\"NewModuleRootManager\" inherit-compiler-output=\"true\">\n-    <exclude-output />\n+<module org.jetbrains.idea.maven.project.MavenProjectsManager.isMavenModule=\"true\" type=\"JAVA_MODULE\" version=\"4\">\n+  <component name=\"NewModuleRootManager\" LANGUAGE_LEVEL=\"JDK_15\">\n+    <output url=\"file://$MODULE_DIR$/target/classes\" />\n+    <output-test url=\"file://$MODULE_DIR$/target/test-classes\" />\n     <content url=\"file://$MODULE_DIR$\">\n-      <sourceFolder url=\"file://$MODULE_DIR$/src\" isTestSource=\"false\" />\n+      <sourceFolder url=\"file://$MODULE_DIR$/src/main/java\" isTestSource=\"false\" />\n+      <sourceFolder url=\"file://$MODULE_DIR$/src/test/java\" isTestSource=\"true\" />\n+      <sourceFolder url=\"file://$MODULE_DIR$/src/test/resources\" type=\"java-test-resource\" />\n+      <excludeFolder url=\"file://$MODULE_DIR$/target\" />\n     </content>\n     <orderEntry type=\"inheritedJdk\" />\n     <orderEntry type=\"sourceFolder\" forTests=\"false\" />\n+    <orderEntry type=\"library\" name=\"Maven: org.seleniumhq.selenium:selenium-java:3.141.59\" level=\"project\" />\n+    <orderEntry type=\"library\" name=\"Maven: org.seleniumhq.selenium:selenium-api:3.141.59\" level=\"project\" />\n+    <orderEntry type=\"library\" name=\"Maven: org.seleniumhq.selenium:selenium-chrome-driver:3.141.59\" level=\"project\" />\n+    <orderEntry type=\"library\" name=\"Maven: org.seleniumhq.selenium:selenium-edge-driver:3.141.59\" level=\"project\" />\n+    <orderEntry type=\"library\" name=\"Maven: org.seleniumhq.selenium:selenium-firefox-driver:3.141.59\" level=\"project\" />\n+    <orderEntry type=\"library\" name=\"Maven: org.seleniumhq.selenium:selenium-ie-driver:3.141.59\" level=\"project\" />\n+    <orderEntry type=\"library\" name=\"Maven: org.seleniumhq.selenium:selenium-opera-driver:3.141.59\" level=\"project\" />\n+    <orderEntry type=\"library\" name=\"Maven: org.seleniumhq.selenium:selenium-remote-driver:3.141.59\" level=\"project\" />\n+    <orderEntry type=\"library\" name=\"Maven: org.seleniumhq.selenium:selenium-safari-driver:3.141.59\" level=\"project\" />\n+    <orderEntry type=\"library\" name=\"Maven: org.seleniumhq.selenium:selenium-support:3.141.59\" level=\"project\" />\n+    <orderEntry type=\"library\" name=\"Maven: net.bytebuddy:byte-buddy:1.8.15\" level=\"project\" />\n+    <orderEntry type=\"library\" name=\"Maven: org.apache.commons:commons-exec:1.3\" level=\"project\" />\n+    <orderEntry type=\"library\" name=\"Maven: com.google.guava:guava:25.0-jre\" level=\"project\" />\n+    <orderEntry type=\"library\" name=\"Maven: com.google.code.findbugs:jsr305:1.3.9\" level=\"project\" />\n+    <orderEntry type=\"library\" name=\"Maven: org.checkerframework:checker-compat-qual:2.0.0\" level=\"project\" />\n+    <orderEntry type=\"library\" name=\"Maven: com.google.errorprone:error_prone_annotations:2.1.3\" level=\"project\" />\n+    <orderEntry type=\"library\" name=\"Maven: com.google.j2objc:j2objc-annotations:1.1\" level=\"project\" />\n+    <orderEntry type=\"library\" name=\"Maven: org.codehaus.mojo:animal-sniffer-annotations:1.14\" level=\"project\" />\n+    <orderEntry type=\"library\" name=\"Maven: com.squareup.okhttp3:okhttp:3.11.0\" level=\"project\" />\n+    <orderEntry type=\"library\" name=\"Maven: com.squareup.okio:okio:1.14.0\" level=\"project\" />\n+    <orderEntry type=\"library\" name=\"Maven: io.github.bonigarcia:webdrivermanager:4.3.1\" level=\"project\" />\n+    <orderEntry type=\"library\" name=\"Maven: org.slf4j:slf4j-api:1.7.30\" level=\"project\" />\n+    <orderEntry type=\"library\" name=\"Maven: commons-io:commons-io:2.8.0\" level=\"project\" />\n+    <orderEntry type=\"library\" name=\"Maven: com.google.code.gson:gson:2.8.6\" level=\"project\" />\n+    <orderEntry type=\"library\" name=\"Maven: org.apache.commons:commons-lang3:3.11\" level=\"project\" />\n+    <orderEntry type=\"library\" name=\"Maven: org.apache.httpcomponents.client5:httpclient5:5.0.3\" level=\"project\" />\n+    <orderEntry type=\"library\" name=\"Maven: org.apache.httpcomponents.core5:httpcore5:5.0.2\" level=\"project\" />\n+    <orderEntry type=\"library\" name=\"Maven: org.apache.httpcomponents.core5:httpcore5-h2:5.0.2\" level=\"project\" />\n+    <orderEntry type=\"library\" name=\"Maven: commons-codec:commons-codec:1.13\" level=\"project\" />\n+    <orderEntry type=\"library\" name=\"Maven: org.rauschig:jarchivelib:1.1.0\" level=\"project\" />\n+    <orderEntry type=\"library\" name=\"Maven: org.apache.commons:commons-compress:1.20\" level=\"project\" />\n+    <orderEntry type=\"library\" name=\"Maven: org.jsoup:jsoup:1.13.1\" level=\"project\" />\n+    <orderEntry type=\"library\" scope=\"TEST\" name=\"Maven: org.testng:testng:7.3.0\" level=\"project\" />\n+    <orderEntry type=\"library\" scope=\"TEST\" name=\"Maven: com.beust:jcommander:1.78\" level=\"project\" />\n+    <orderEntry type=\"library\" scope=\"TEST\" name=\"Maven: org.apache.ant:ant:1.10.3\" level=\"project\" />\n+    <orderEntry type=\"library\" scope=\"TEST\" name=\"Maven: org.apache.ant:ant-launcher:1.10.3\" level=\"project\" />\n+    <orderEntry type=\"library\" scope=\"TEST\" name=\"Maven: com.google.inject:guice:no_aop:4.2.2\" level=\"project\" />\n+    <orderEntry type=\"library\" scope=\"TEST\" name=\"Maven: javax.inject:javax.inject:1\" level=\"project\" />\n+    <orderEntry type=\"library\" scope=\"TEST\" name=\"Maven: aopalliance:aopalliance:1.0\" level=\"project\" />\n+    <orderEntry type=\"library\" scope=\"TEST\" name=\"Maven: org.yaml:snakeyaml:1.21\" level=\"project\" />\n+    <orderEntry type=\"library\" scope=\"TEST\" name=\"Maven: io.qameta.allure:allure-testng:2.13.8\" level=\"project\" />\n+    <orderEntry type=\"library\" scope=\"TEST\" name=\"Maven: io.qameta.allure:allure-java-commons:2.13.8\" level=\"project\" />\n+    <orderEntry type=\"library\" scope=\"TEST\" name=\"Maven: io.qameta.allure:allure-model:2.13.8\" level=\"project\" />\n+    <orderEntry type=\"library\" name=\"Maven: com.fasterxml.jackson.core:jackson-databind:2.11.3\" level=\"project\" />\n+    <orderEntry type=\"library\" name=\"Maven: com.fasterxml.jackson.core:jackson-core:2.11.3\" level=\"project\" />\n+    <orderEntry type=\"library\" scope=\"TEST\" name=\"Maven: org.apache.tika:tika-core:1.24.1\" level=\"project\" />\n+    <orderEntry type=\"library\" scope=\"TEST\" name=\"Maven: org.jooq:joor-java-8:0.9.13\" level=\"project\" />\n+    <orderEntry type=\"library\" name=\"Maven: junit:junit:4.13.1\" level=\"project\" />\n+    <orderEntry type=\"library\" name=\"Maven: org.hamcrest:hamcrest-core:1.3\" level=\"project\" />\n+    <orderEntry type=\"library\" name=\"Maven: com.fasterxml.jackson.core:jackson-annotations:2.11.3\" level=\"project\" />\n+    <orderEntry type=\"library\" name=\"Maven: io.rest-assured:json-schema-validator:4.3.3\" level=\"project\" />\n+    <orderEntry type=\"library\" name=\"Maven: com.github.java-json-tools:json-schema-validator:2.2.14\" level=\"project\" />\n+    <orderEntry type=\"library\" name=\"Maven: com.github.java-json-tools:jackson-coreutils-equivalence:1.0\" level=\"project\" />\n+    <orderEntry type=\"library\" name=\"Maven: com.github.java-json-tools:jackson-coreutils:2.0\" level=\"project\" />\n+    <orderEntry type=\"library\" name=\"Maven: com.github.java-json-tools:msg-simple:1.2\" level=\"project\" />\n+    <orderEntry type=\"library\" name=\"Maven: com.github.java-json-tools:btf:1.3\" level=\"project\" />\n+    <orderEntry type=\"library\" name=\"Maven: com.github.java-json-tools:json-schema-core:1.2.14\" level=\"project\" />\n+    <orderEntry type=\"library\" name=\"Maven: com.github.java-json-tools:uri-template:0.10\" level=\"project\" />\n+    <orderEntry type=\"library\" name=\"Maven: org.mozilla:rhino:1.7.7.2\" level=\"project\" />\n+    <orderEntry type=\"library\" name=\"Maven: com.sun.mail:mailapi:1.6.2\" level=\"project\" />\n+    <orderEntry type=\"library\" name=\"Maven: joda-time:joda-time:2.10.5\" level=\"project\" />\n+    <orderEntry type=\"library\" name=\"Maven: com.googlecode.libphonenumber:libphonenumber:8.11.1\" level=\"project\" />\n+    <orderEntry type=\"library\" name=\"Maven: net.sf.jopt-simple:jopt-simple:5.0.4\" level=\"project\" />\n+    <orderEntry type=\"library\" name=\"Maven: org.hamcrest:hamcrest:2.1\" level=\"project\" />\n+    <orderEntry type=\"library\" scope=\"TEST\" name=\"Maven: io.rest-assured:rest-assured:4.3.3\" level=\"project\" />\n+    <orderEntry type=\"library\" scope=\"TEST\" name=\"Maven: org.codehaus.groovy:groovy:3.0.7\" level=\"project\" />\n+    <orderEntry type=\"library\" scope=\"TEST\" name=\"Maven: org.codehaus.groovy:groovy-xml:3.0.7\" level=\"project\" />\n+    <orderEntry type=\"library\" scope=\"TEST\" name=\"Maven: org.apache.httpcomponents:httpclient:4.5.3\" level=\"project\" />\n+    <orderEntry type=\"library\" scope=\"TEST\" name=\"Maven: org.apache.httpcomponents:httpcore:4.4.6\" level=\"project\" />\n+    <orderEntry type=\"library\" scope=\"TEST\" name=\"Maven: commons-logging:commons-logging:1.2\" level=\"project\" />\n+    <orderEntry type=\"library\" scope=\"TEST\" name=\"Maven: org.apache.httpcomponents:httpmime:4.5.3\" level=\"project\" />\n+    <orderEntry type=\"library\" scope=\"TEST\" name=\"Maven: org.ccil.cowan.tagsoup:tagsoup:1.2.1\" level=\"project\" />\n+    <orderEntry type=\"library\" scope=\"TEST\" name=\"Maven: io.rest-assured:json-path:4.3.3\" level=\"project\" />\n+    <orderEntry type=\"library\" scope=\"TEST\" name=\"Maven: org.codehaus.groovy:groovy-json:3.0.7\" level=\"project\" />\n+    <orderEntry type=\"library\" scope=\"TEST\" name=\"Maven: io.rest-assured:rest-assured-common:4.3.3\" level=\"project\" />\n+    <orderEntry type=\"library\" scope=\"TEST\" name=\"Maven: io.rest-assured:xml-path:4.3.3\" level=\"project\" />\n+    <orderEntry type=\"library\" scope=\"TEST\" name=\"Maven: jakarta.xml.bind:jakarta.xml.bind-api:2.3.3\" level=\"project\" />\n+    <orderEntry type=\"library\" scope=\"TEST\" name=\"Maven: jakarta.activation:jakarta.activation-api:1.2.2\" level=\"project\" />\n+    <orderEntry type=\"library\" scope=\"TEST\" name=\"Maven: com.sun.xml.bind:jaxb-impl:2.3.3\" level=\"project\" />\n   </component>\n </module>\n\\ No newline at end of file"
  },
  {
    "sha": "b958fce93cf1d70de73418e25291063eb3b0dc37",
    "filename": "pom.xml",
    "status": "added",
    "additions": 92,
    "deletions": 0,
    "changes": 92,
    "blob_url": "https://github.com/krettt/KretOleg/blob/681451ce8bc7845de180e20b631464b9e9cdbdaa/pom.xml",
    "raw_url": "https://github.com/krettt/KretOleg/raw/681451ce8bc7845de180e20b631464b9e9cdbdaa/pom.xml",
    "contents_url": "https://api.github.com/repos/krettt/KretOleg/contents/pom.xml?ref=681451ce8bc7845de180e20b631464b9e9cdbdaa",
    "patch": "@@ -0,0 +1,92 @@\n+<?xml version=\"1.0\" encoding=\"UTF-8\"?>\n+<project xmlns=\"http://maven.apache.org/POM/4.0.0\"\n+         xmlns:xsi=\"http://www.w3.org/2001/XMLSchema-instance\"\n+         xsi:schemaLocation=\"http://maven.apache.org/POM/4.0.0 http://maven.apache.org/xsd/maven-4.0.0.xsd\">\n+    <modelVersion>4.0.0</modelVersion>\n+\n+    <groupId>groupId</groupId>\n+    <artifactId>KretOleg</artifactId>\n+    <version>1.0-SNAPSHOT</version>\n+\n+    <dependencies>\n+        <dependency>\n+            <groupId>org.seleniumhq.selenium</groupId>\n+            <artifactId>selenium-java</artifactId>\n+            <version>3.141.59</version>\n+        </dependency>\n+        <dependency>\n+            <groupId>io.github.bonigarcia</groupId>\n+            <artifactId>webdrivermanager</artifactId>\n+            <version>4.3.1</version>\n+        </dependency>\n+        <dependency>\n+            <groupId>org.testng</groupId>\n+            <artifactId>testng</artifactId>\n+            <version>7.3.0</version>\n+            <scope>test</scope>\n+        </dependency>\n+        <dependency>\n+            <groupId>io.qameta.allure</groupId>\n+            <artifactId>allure-testng</artifactId>\n+            <version>2.13.8</version>\n+            <scope>test</scope>\n+        </dependency>\n+        <dependency>\n+            <groupId>junit</groupId>\n+            <artifactId>junit</artifactId>\n+            <version>4.13.1</version>\n+            <scope>compile</scope>\n+        </dependency>\n+        <dependency>\n+            <groupId>com.fasterxml.jackson.core</groupId>\n+            <artifactId>jackson-annotations</artifactId>\n+            <version>2.11.3</version>\n+            <scope>compile</scope>\n+        </dependency>\n+        <dependency>\n+            <groupId>io.rest-assured</groupId>\n+            <artifactId>json-schema-validator</artifactId>\n+            <version>4.3.3</version>\n+        </dependency>\n+        <dependency>\n+            <groupId>io.rest-assured</groupId>\n+            <artifactId>rest-assured</artifactId>\n+            <version>4.3.3</version>\n+            <scope>test</scope>\n+        </dependency>\n+    </dependencies>\n+\n+    <build>\n+        <plugins>\n+            <plugin>\n+                <groupId>org.apache.maven.plugins</groupId>\n+                <artifactId>maven-compiler-plugin</artifactId>\n+                <version>3.6.0</version>\n+                <configuration>\n+                    <source>15</source>\n+                    <target>15</target>\n+                </configuration>\n+            </plugin>\n+            <plugin>\n+                <groupId>io.qameta.allure</groupId>\n+                <artifactId>allure-maven</artifactId>\n+                <version>2.10.0</version>\n+                <configuration>\n+                    <resultsDirectory>${project.basedir}${file.separator}allure-results</resultsDirectory>\n+                    <reportDirectory>${project.basedir}${file.separator}allure-report</reportDirectory>\n+                    <reportVersion>2.13.8</reportVersion>\n+                </configuration>\n+            </plugin>\n+\n+\n+        </plugins>\n+    </build>\n+\n+    <properties>\n+        <maven.compiler.source>15</maven.compiler.source>\n+        <maven.compiler.target>15</maven.compiler.target>\n+        <allure-maven.version>2.10.0</allure-maven.version>\n+\n+    </properties>\n+    \n+</project>\n\\ No newline at end of file"
  },
  {
    "sha": "3195f3cbbd1eab65bad42d6b050214ac9c118dfd",
    "filename": "src/main/java/rest/assured/Engineer.java",
    "status": "added",
    "additions": 81,
    "deletions": 0,
    "changes": 81,
    "blob_url": "https://github.com/krettt/KretOleg/blob/681451ce8bc7845de180e20b631464b9e9cdbdaa/src/main/java/rest/assured/Engineer.java",
    "raw_url": "https://github.com/krettt/KretOleg/raw/681451ce8bc7845de180e20b631464b9e9cdbdaa/src/main/java/rest/assured/Engineer.java",
    "contents_url": "https://api.github.com/repos/krettt/KretOleg/contents/src/main/java/rest/assured/Engineer.java?ref=681451ce8bc7845de180e20b631464b9e9cdbdaa",
    "patch": "@@ -0,0 +1,81 @@\n+package rest.assured;\n+\n+public class Engineer {\n+\n+    private String constructorId;\n+    private String url;\n+    private String name;\n+    private String nationality;\n+\n+    public Engineer(){}\n+    public Engineer(String constructorId, String url, String name, String nationality) {\n+        this.constructorId = constructorId;\n+        this.url = url;\n+        this.name = name;\n+        this.nationality = nationality;\n+    }\n+\n+    @Override\n+    public boolean equals(Object o) {\n+        if (this == o) return true;\n+        if (o == null || getClass() != o.getClass()) return false;\n+\n+        Engineer engineer = (Engineer) o;\n+\n+        if (constructorId != null ? !constructorId.equals(engineer.constructorId) : engineer.constructorId != null)\n+            return false;\n+        if (url != null ? !url.equals(engineer.url) : engineer.url != null) return false;\n+        if (name != null ? !name.equals(engineer.name) : engineer.name != null) return false;\n+        return nationality != null ? nationality.equals(engineer.nationality) : engineer.nationality == null;\n+    }\n+\n+    @Override\n+    public int hashCode() {\n+        int result = constructorId != null ? constructorId.hashCode() : 0;\n+        result = 31 * result + (url != null ? url.hashCode() : 0);\n+        result = 31 * result + (name != null ? name.hashCode() : 0);\n+        result = 31 * result + (nationality != null ? nationality.hashCode() : 0);\n+        return result;\n+    }\n+    public String getConstructorId() {\n+        return constructorId;\n+    }\n+\n+    public void setConstructorId(String constructorId) {\n+        this.constructorId = constructorId;\n+    }\n+\n+    public String getUrl() {\n+        return url;\n+    }\n+\n+    public void setUrl(String url) {\n+        this.url = url;\n+    }\n+\n+    public String getName() {\n+        return name;\n+    }\n+\n+    public void setName(String name) {\n+        this.name = name;\n+    }\n+\n+    public String getNationality() {\n+        return nationality;\n+    }\n+\n+    public void setNationality(String nationality) {\n+        this.nationality = nationality;\n+    }\n+\n+    @Override\n+    public String toString() {\n+        return \"{\" +\n+                \" constructorId \" + constructorId + \"\\'\" +\n+                \" url \" + url + \"\\'\" +\n+                \" name \" + name + \"\\'\" +\n+                \" nationality \" + nationality\n+                + \"}\";\n+    }\n+}"
  },
  {
    "sha": "1db0fbfae1cae3f9003bd59ce864900618748ba2",
    "filename": "src/test/java/rest/assured/RestAssuredTest.java",
    "status": "added",
    "additions": 51,
    "deletions": 0,
    "changes": 51,
    "blob_url": "https://github.com/krettt/KretOleg/blob/681451ce8bc7845de180e20b631464b9e9cdbdaa/src/test/java/rest/assured/RestAssuredTest.java",
    "raw_url": "https://github.com/krettt/KretOleg/raw/681451ce8bc7845de180e20b631464b9e9cdbdaa/src/test/java/rest/assured/RestAssuredTest.java",
    "contents_url": "https://api.github.com/repos/krettt/KretOleg/contents/src/test/java/rest/assured/RestAssuredTest.java?ref=681451ce8bc7845de180e20b631464b9e9cdbdaa",
    "patch": "@@ -0,0 +1,51 @@\n+package rest.assured;\n+\n+import io.restassured.response.Response;\n+import org.hamcrest.Matchers;\n+import org.testng.annotations.BeforeClass;\n+import org.testng.annotations.Test;\n+\n+import java.util.Arrays;\n+import java.util.List;\n+\n+import static io.restassured.RestAssured.given;\n+import static io.restassured.module.jsv.JsonSchemaValidator.matchesJsonSchemaInClasspath;\n+import static org.hamcrest.Matchers.equalTo;\n+import static org.testng.AssertJUnit.assertTrue;\n+\n+public class RestAssuredTest {\n+    private static final String URL = \"http://ergast.com/api/f1/2010/constructors.json\";\n+    Response responseURL = given().get(URL);\n+    private final static List<String> constructorId = Arrays.asList(\"ferrari\", \"force_india\",\n+            \"hrt\", \"lotus_racing\", \"mclaren\", \"mercedes\", \"red_bull\",\n+            \"renault\", \"sauber\", \"toro_rosso\", \"virgin\", \"williams\");\n+\n+    @BeforeClass\n+    public void checkURL() {\n+        responseURL.then().statusCode(200);\n+    }\n+\n+    @Test\n+    public void checkAmountOfRecordInResponse() {\n+        responseURL.then().assertThat().body(\"MRData.ConstructorTable.Constructors.constructorId\",\n+                Matchers.hasSize(12));\n+    }\n+\n+    @Test\n+    public void checkConstructorsCompany() {\n+        responseURL.then().assertThat().body(\"MRData.ConstructorTable.Constructors.constructorId\",\n+                equalTo(constructorId));\n+    }\n+\n+    @Test\n+    public void checkMercedes() {\n+        List<Engineer> list = responseURL.jsonPath().getList(\"MRData.ConstructorTable.Constructors\", Engineer.class);\n+        assertTrue(list.stream().anyMatch(item -> item.equals(new Engineer(\"mercedes\",\n+                \"http://en.wikipedia.org/wiki/Mercedes-Benz_in_Formula_One\", \"Mercedes\", \"German\"))));\n+    }\n+\n+    @Test\n+    public void doValidationResponseOfJsonScheme() {\n+        responseURL.then().assertThat().body(matchesJsonSchemaInClasspath(\"Constructors-schema.json\"));\n+    }\n+}"
  },
  {
    "sha": "3cbb72bfe422a7d0cf20c151a97091c9e6fde1ff",
    "filename": "src/test/resources/Constructors-schema.json",
    "status": "added",
    "additions": 334,
    "deletions": 0,
    "changes": 334,
    "blob_url": "https://github.com/krettt/KretOleg/blob/681451ce8bc7845de180e20b631464b9e9cdbdaa/src/test/resources/Constructors-schema.json",
    "raw_url": "https://github.com/krettt/KretOleg/raw/681451ce8bc7845de180e20b631464b9e9cdbdaa/src/test/resources/Constructors-schema.json",
    "contents_url": "https://api.github.com/repos/krettt/KretOleg/contents/src/test/resources/Constructors-schema.json?ref=681451ce8bc7845de180e20b631464b9e9cdbdaa",
    "patch": "@@ -0,0 +1,334 @@\n+{\n+  \"$schema\": \"http://json-schema.org/draft-04/schema#\",\n+  \"type\": \"object\",\n+  \"properties\": {\n+    \"MRData\": {\n+      \"type\": \"object\",\n+      \"properties\": {\n+        \"xmlns\": {\n+          \"type\": \"string\"\n+        },\n+        \"series\": {\n+          \"type\": \"string\"\n+        },\n+        \"url\": {\n+          \"type\": \"string\"\n+        },\n+        \"limit\": {\n+          \"type\": \"string\"\n+        },\n+        \"offset\": {\n+          \"type\": \"string\"\n+        },\n+        \"total\": {\n+          \"type\": \"string\"\n+        },\n+        \"ConstructorTable\": {\n+          \"type\": \"object\",\n+          \"properties\": {\n+            \"season\": {\n+              \"type\": \"string\"\n+            },\n+            \"Constructors\": {\n+              \"type\": \"array\",\n+              \"items\": [\n+                {\n+                  \"type\": \"object\",\n+                  \"properties\": {\n+                    \"constructorId\": {\n+                      \"type\": \"string\"\n+                    },\n+                    \"url\": {\n+                      \"type\": \"string\"\n+                    },\n+                    \"name\": {\n+                      \"type\": \"string\"\n+                    },\n+                    \"nationality\": {\n+                      \"type\": \"string\"\n+                    }\n+                  },\n+                  \"required\": [\n+                    \"constructorId\",\n+                    \"url\",\n+                    \"name\",\n+                    \"nationality\"\n+                  ]\n+                },\n+                {\n+                  \"type\": \"object\",\n+                  \"properties\": {\n+                    \"constructorId\": {\n+                      \"type\": \"string\"\n+                    },\n+                    \"url\": {\n+                      \"type\": \"string\"\n+                    },\n+                    \"name\": {\n+                      \"type\": \"string\"\n+                    },\n+                    \"nationality\": {\n+                      \"type\": \"string\"\n+                    }\n+                  },\n+                  \"required\": [\n+                    \"constructorId\",\n+                    \"url\",\n+                    \"name\",\n+                    \"nationality\"\n+                  ]\n+                },\n+                {\n+                  \"type\": \"object\",\n+                  \"properties\": {\n+                    \"constructorId\": {\n+                      \"type\": \"string\"\n+                    },\n+                    \"url\": {\n+                      \"type\": \"string\"\n+                    },\n+                    \"name\": {\n+                      \"type\": \"string\"\n+                    },\n+                    \"nationality\": {\n+                      \"type\": \"string\"\n+                    }\n+                  },\n+                  \"required\": [\n+                    \"constructorId\",\n+                    \"url\",\n+                    \"name\",\n+                    \"nationality\"\n+                  ]\n+                },\n+                {\n+                  \"type\": \"object\",\n+                  \"properties\": {\n+                    \"constructorId\": {\n+                      \"type\": \"string\"\n+                    },\n+                    \"url\": {\n+                      \"type\": \"string\"\n+                    },\n+                    \"name\": {\n+                      \"type\": \"string\"\n+                    },\n+                    \"nationality\": {\n+                      \"type\": \"string\"\n+                    }\n+                  },\n+                  \"required\": [\n+                    \"constructorId\",\n+                    \"url\",\n+                    \"name\",\n+                    \"nationality\"\n+                  ]\n+                },\n+                {\n+                  \"type\": \"object\",\n+                  \"properties\": {\n+                    \"constructorId\": {\n+                      \"type\": \"string\"\n+                    },\n+                    \"url\": {\n+                      \"type\": \"string\"\n+                    },\n+                    \"name\": {\n+                      \"type\": \"string\"\n+                    },\n+                    \"nationality\": {\n+                      \"type\": \"string\"\n+                    }\n+                  },\n+                  \"required\": [\n+                    \"constructorId\",\n+                    \"url\",\n+                    \"name\",\n+                    \"nationality\"\n+                  ]\n+                },\n+                {\n+                  \"type\": \"object\",\n+                  \"properties\": {\n+                    \"constructorId\": {\n+                      \"type\": \"string\"\n+                    },\n+                    \"url\": {\n+                      \"type\": \"string\"\n+                    },\n+                    \"name\": {\n+                      \"type\": \"string\"\n+                    },\n+                    \"nationality\": {\n+                      \"type\": \"string\"\n+                    }\n+                  },\n+                  \"required\": [\n+                    \"constructorId\",\n+                    \"url\",\n+                    \"name\",\n+                    \"nationality\"\n+                  ]\n+                },\n+                {\n+                  \"type\": \"object\",\n+                  \"properties\": {\n+                    \"constructorId\": {\n+                      \"type\": \"string\"\n+                    },\n+                    \"url\": {\n+                      \"type\": \"string\"\n+                    },\n+                    \"name\": {\n+                      \"type\": \"string\"\n+                    },\n+                    \"nationality\": {\n+                      \"type\": \"string\"\n+                    }\n+                  },\n+                  \"required\": [\n+                    \"constructorId\",\n+                    \"url\",\n+                    \"name\",\n+                    \"nationality\"\n+                  ]\n+                },\n+                {\n+                  \"type\": \"object\",\n+                  \"properties\": {\n+                    \"constructorId\": {\n+                      \"type\": \"string\"\n+                    },\n+                    \"url\": {\n+                      \"type\": \"string\"\n+                    },\n+                    \"name\": {\n+                      \"type\": \"string\"\n+                    },\n+                    \"nationality\": {\n+                      \"type\": \"string\"\n+                    }\n+                  },\n+                  \"required\": [\n+                    \"constructorId\",\n+                    \"url\",\n+                    \"name\",\n+                    \"nationality\"\n+                  ]\n+                },\n+                {\n+                  \"type\": \"object\",\n+                  \"properties\": {\n+                    \"constructorId\": {\n+                      \"type\": \"string\"\n+                    },\n+                    \"url\": {\n+                      \"type\": \"string\"\n+                    },\n+                    \"name\": {\n+                      \"type\": \"string\"\n+                    },\n+                    \"nationality\": {\n+                      \"type\": \"string\"\n+                    }\n+                  },\n+                  \"required\": [\n+                    \"constructorId\",\n+                    \"url\",\n+                    \"name\",\n+                    \"nationality\"\n+                  ]\n+                },\n+                {\n+                  \"type\": \"object\",\n+                  \"properties\": {\n+                    \"constructorId\": {\n+                      \"type\": \"string\"\n+                    },\n+                    \"url\": {\n+                      \"type\": \"string\"\n+                    },\n+                    \"name\": {\n+                      \"type\": \"string\"\n+                    },\n+                    \"nationality\": {\n+                      \"type\": \"string\"\n+                    }\n+                  },\n+                  \"required\": [\n+                    \"constructorId\",\n+                    \"url\",\n+                    \"name\",\n+                    \"nationality\"\n+                  ]\n+                },\n+                {\n+                  \"type\": \"object\",\n+                  \"properties\": {\n+                    \"constructorId\": {\n+                      \"type\": \"string\"\n+                    },\n+                    \"url\": {\n+                      \"type\": \"string\"\n+                    },\n+                    \"name\": {\n+                      \"type\": \"string\"\n+                    },\n+                    \"nationality\": {\n+                      \"type\": \"string\"\n+                    }\n+                  },\n+                  \"required\": [\n+                    \"constructorId\",\n+                    \"url\",\n+                    \"name\",\n+                    \"nationality\"\n+                  ]\n+                },\n+                {\n+                  \"type\": \"object\",\n+                  \"properties\": {\n+                    \"constructorId\": {\n+                      \"type\": \"string\"\n+                    },\n+                    \"url\": {\n+                      \"type\": \"string\"\n+                    },\n+                    \"name\": {\n+                      \"type\": \"string\"\n+                    },\n+                    \"nationality\": {\n+                      \"type\": \"string\"\n+                    }\n+                  },\n+                  \"required\": [\n+                    \"constructorId\",\n+                    \"url\",\n+                    \"name\",\n+                    \"nationality\"\n+                  ]\n+                }\n+              ]\n+            }\n+          },\n+          \"required\": [\n+            \"season\",\n+            \"Constructors\"\n+          ]\n+        }\n+      },\n+      \"required\": [\n+        \"xmlns\",\n+        \"series\",\n+        \"url\",\n+        \"limit\",\n+        \"offset\",\n+        \"total\",\n+        \"ConstructorTable\"\n+      ]\n+    }\n+  },\n+  \"required\": [\n+    \"MRData\"\n+  ]\n+}\n\\ No newline at end of file"
  }
]
