[
  {
    "sha": "5fa13657ee7b1db88d68fa3417572d0eccebdb51",
    "filename": "nanoha-base/pom.xml",
    "status": "modified",
    "additions": 1,
    "deletions": 1,
    "changes": 2,
    "blob_url": "https://github.com/nayyang/nanoha-as/blob/9848515915ab17b62ac16fdf0004326bda29f8ed/nanoha-base/pom.xml",
    "raw_url": "https://github.com/nayyang/nanoha-as/raw/9848515915ab17b62ac16fdf0004326bda29f8ed/nanoha-base/pom.xml",
    "contents_url": "https://api.github.com/repos/nayyang/nanoha-as/contents/nanoha-base/pom.xml?ref=9848515915ab17b62ac16fdf0004326bda29f8ed",
    "patch": "@@ -23,7 +23,7 @@\n         <junit.version>3.8.1</junit.version>\n         <log4j.version>1.2.17</log4j.version>\n         <slf4j.version>1.7.5</slf4j.version>\n-        <poi.version>3.10-FINAL</poi.version>\n+        <poi.version>5.0.0</poi.version>\n         <commons-lang3.version>3.1</commons-lang3.version>\n         <commons-io.version>2.4</commons-io.version>\n         <commons-codec.version>1.8</commons-codec.version>"
  }
]
