[
  {
    "sha": "cbcf5285d0011fdaca5d0bbed00883b5b301c7d4",
    "filename": ".github/settings.yml",
    "status": "added",
    "additions": 134,
    "deletions": 0,
    "changes": 134,
    "blob_url": "https://github.com/Andi-IM/desktop-project/blob/b7c15fd2564917cf75d892449f5c403b52e58fd1/.github/settings.yml",
    "raw_url": "https://github.com/Andi-IM/desktop-project/raw/b7c15fd2564917cf75d892449f5c403b52e58fd1/.github/settings.yml",
    "contents_url": "https://api.github.com/repos/Andi-IM/desktop-project/contents/.github/settings.yml?ref=b7c15fd2564917cf75d892449f5c403b52e58fd1",
    "patch": "@@ -0,0 +1,134 @@\n+# These settings are synced to GitHub by https://probot.github.io/apps/settings/\n+\n+repository:\n+  # See https://developer.github.com/v3/repos/#edit for all available settings.\n+\n+  # The name of the repository. Changing this will rename the repository\n+  name: desktop-project\n+\n+  # A short description of the repository that will show up on GitHub\n+  description: Sample Project Kelompok\n+\n+  # A comma-separated list of topics to set on the repository\n+  topics: projectdesktop, trplpnp, kelompok5trpl2apnp\n+\n+  # Either `true` to make the repository private, or `false` to make it public.\n+  private: false\n+\n+  # Either `true` to enable issues for this repository, `false` to disable them.\n+  has_issues: true\n+\n+  # Either `true` to enable projects for this repository, or `false` to disable them.\n+  # If projects are disabled for the organization, passing `true` will cause an API error.\n+  has_projects: true\n+\n+  # Either `true` to enable the wiki for this repository, `false` to disable it.\n+  has_wiki: true\n+\n+  # Either `true` to enable downloads for this repository, `false` to disable them.\n+  has_downloads: true\n+\n+  # Updates the default branch for this repository.\n+  default_branch: main\n+\n+  # Either `true` to allow squash-merging pull requests, or `false` to prevent\n+  # squash-merging.\n+  allow_squash_merge: true\n+\n+  # Either `true` to allow merging pull requests with a merge commit, or `false`\n+  # to prevent merging pull requests with merge commits.\n+  allow_merge_commit: true\n+\n+  # Either `true` to allow rebase-merging pull requests, or `false` to prevent\n+  # rebase-merging.\n+  allow_rebase_merge: true\n+\n+# Labels: define labels for Issues and Pull Requests\n+labels:\n+  - name: bug\n+    color: CC0000\n+    description: An issue with the system 🐛.\n+\n+  - name: feature\n+    # If including a `#`, make sure to wrap it with quotes!\n+    color: '#336699'\n+    description: New functionality.\n+\n+  - name: GitHub\n+    color: '#000000'\n+    description: GitHub context.\n+\n+  - name: info\n+    color: '#0B0A4A'\n+    description: Something want to tell.\n+\n+  - name: Need Help    \n+    oldname: first-timers-only \n+\n+  - name: Trello\n+    color: '#1D76DB'\n+    description: Trello Context.  \n+\n+# Milestones: define milestones for Issues and Pull Requests\n+milestones:\n+  - title: Gabung ke Github\n+    description: memastikan semua anggota collab bergabung\n+    # The state of the milestone. Either `open` or `closed`\n+    state: closed\n+\n+  - title: Mulai Real Project!\n+    description: memulai tahap production!\n+    state: closed  \n+\n+# Collaborators: give specific users access to this repository.\n+# See https://developer.github.com/v3/repos/collaborators/#add-user-as-a-collaborator for available options\n+collaborators:\n+  - username: Andi-IM\n+    # Note: Only valid on organization-owned repositories.\n+    # The permission to grant the collaborator. Can be one of:\n+    # * `pull` - can pull, but not push to or administer this repository.\n+    # * `push` - can pull and push, but not administer this repository.\n+    # * `admin` - can pull, push and administer this repository.\n+    # * `maintain` - Recommended for project managers who need to manage the repository without access to sensitive or destructive actions.\n+    # * `triage` - Recommended for contributors who need to proactively manage issues and pull requests without write access.\n+    permission: admin\n+\n+  - username: hakkansy\n+    permission: push\n+  \n+  - username: luthfiyyahnisaa\n+    permission: push\n+  \n+  - username: abidasshidiqienugraha\n+    permission: push    \n+\n+branches:\n+  - name: main\n+    # https://developer.github.com/v3/repos/branches/#update-branch-protection\n+    # Branch Protection settings. Set to null to disable\n+    protection:\n+      # Required. Require at least one approving review on a pull request, before merging. Set to null to disable.\n+      required_pull_request_reviews:\n+        # The number of approvals required. (1-6)\n+        required_approving_review_count: 1\n+        # Dismiss approved reviews automatically when a new commit is pushed.\n+        dismiss_stale_reviews: true\n+        # Blocks merge until code owners have reviewed.\n+        require_code_owner_reviews: true\n+        # Specify which users and teams can dismiss pull request reviews. Pass an empty dismissal_restrictions object to disable. User and team dismissal_restrictions are only available for organization-owned repositories. Omit this parameter for personal repositories.\n+        dismissal_restrictions:\n+          users: []\n+          teams: []\n+      # Required. Require status checks to pass before merging. Set to null to disable\n+      required_status_checks:\n+        # Required. Require branches to be up to date before merging.\n+        strict: true\n+        # Required. The list of status checks to require in order to merge into this branch\n+        contexts: []\n+      # Required. Enforce all configured restrictions for administrators. Set to true to enforce required status checks for repository administrators. Set to null to disable.\n+      enforce_admins: true\n+      # Required. Restrict who can push to this branch. Team and user restrictions are only available for organization-owned repositories. Set to null to disable.\n+      restrictions:\n+        apps: []\n+        users: []\n+        teams: []\n\\ No newline at end of file"
  },
  {
    "sha": "02c3e8087223d906c86c456535c900d76e7954d5",
    "filename": ".github/workflows/inspector.yml",
    "status": "added",
    "additions": 47,
    "deletions": 0,
    "changes": 47,
    "blob_url": "https://github.com/Andi-IM/desktop-project/blob/b7c15fd2564917cf75d892449f5c403b52e58fd1/.github/workflows/inspector.yml",
    "raw_url": "https://github.com/Andi-IM/desktop-project/raw/b7c15fd2564917cf75d892449f5c403b52e58fd1/.github/workflows/inspector.yml",
    "contents_url": "https://api.github.com/repos/Andi-IM/desktop-project/contents/.github/workflows/inspector.yml?ref=b7c15fd2564917cf75d892449f5c403b52e58fd1",
    "patch": "@@ -0,0 +1,47 @@\n+# This is a basic workflow to help you get started with Actions\n+\n+name: CI\n+\n+# Controls when the action will run. \n+on:\n+  push:\n+    branches: [ main ]\n+  pull_request:\n+    branches: [ main ]\n+\n+# A workflow run is made up of one or more jobs that can run sequentially or in parallel\n+jobs:\n+  # This workflow contains a single job called \"build\"\n+  check-quality:\n+    # The type of runner that the job will run on\n+    runs-on: ubuntu-latest\n+    name: Code Checking...\n+    # Steps represent a sequence of tasks that will be executed as part of the job\n+    steps:\n+      # Runs Code Inspector\n+      - name: Code Inspector GitHub action\n+        id: code-inspector\n+        # You may pin to the exact commit or the version.\n+        # uses: codeinspectorio/github-action@01c818be303e2c4bcec991ca1c51feab753a1e2a\n+        uses: codeinspectorio/github-action@master\n+        with:\n+          # Token to checkout the repository.\n+          repo_token: ${{ secrets.GITHUB_TOKEN }}\n+          # Access key on Code Inspector\n+          code_inspector_access_key: ${{ secrets.CODE_INSPECTOR_ACCESS_KEY }}\n+          # Secret key on Code Inspector\n+          code_inspector_secret_key: ${{ secrets.CODE_INSPECTOR_SECRET_KEY }}\n+          # Minimum grade. Valid options are EXCELLENT, GOOD, NEUTRAL, WARNING, CRITICAL. Leave blank to ignore.\n+          min_quality_grade: 'WARNING' # default is \n+          # Minimum quality score from 0 (worst) to 100 (best)\n+          min_quality_score: '50' # default is 0\n+          # Maximum defect rate per line of code (e.g. 0.01 for 1 defect per 100 lines of code). Leave 0 to ignore.\n+          max_defects_rate: '0.0001' # default is 0\n+          # Maximum number of complex functions rate (e.g. number of complex functions / number of functions). Leave 0 to ignore.\n+          max_complex_functions_rate: '0.0001' # default is 0\n+          # Maximum number of long functions rate (e.g. number of long functions / number of functions). Leave 0 to ignore.\n+          max_long_functions_rate: '0.0001' # default is 0\n+          # Project on code inspector. Will use the preferences of this analysis. Leave blank and no preferences are used\n+          project_name: '' # default is \n+          # Timeout before giving up (in case analysis takes too long). Default is 10 minutes\n+          max_timeout_sec: '600' # default is 600"
  },
  {
    "sha": "1ce3d7925d9625f312085d6b1ce420738849546a",
    "filename": "Andi.java",
    "status": "modified",
    "additions": 9,
    "deletions": 2,
    "changes": 11,
    "blob_url": "https://github.com/Andi-IM/desktop-project/blob/b7c15fd2564917cf75d892449f5c403b52e58fd1/Andi.java",
    "raw_url": "https://github.com/Andi-IM/desktop-project/raw/b7c15fd2564917cf75d892449f5c403b52e58fd1/Andi.java",
    "contents_url": "https://api.github.com/repos/Andi-IM/desktop-project/contents/Andi.java?ref=b7c15fd2564917cf75d892449f5c403b52e58fd1",
    "patch": "@@ -1,7 +1,14 @@\n-public class Andi {\n-    private static String nama = \"Andi\";\n+\n+public class Andi implements GetItem{\n+\n+    private static String nama = \"Andi Irham\";\n \n     public static String getNama() {\n         return nama;\n     }\n+\n+    @Override\n+    public void tampilkan(){\n+        System.out.println(getNama());\n+    }\n }"
  },
  {
    "sha": "2643e96769b064549cf51e1392a4f14870200ef4",
    "filename": "GetItem.java",
    "status": "added",
    "additions": 3,
    "deletions": 0,
    "changes": 3,
    "blob_url": "https://github.com/Andi-IM/desktop-project/blob/b7c15fd2564917cf75d892449f5c403b52e58fd1/GetItem.java",
    "raw_url": "https://github.com/Andi-IM/desktop-project/raw/b7c15fd2564917cf75d892449f5c403b52e58fd1/GetItem.java",
    "contents_url": "https://api.github.com/repos/Andi-IM/desktop-project/contents/GetItem.java?ref=b7c15fd2564917cf75d892449f5c403b52e58fd1",
    "patch": "@@ -0,0 +1,3 @@\n+public interface GetItem {\n+    public void tampilkan();\n+}"
  },
  {
    "sha": "3bfe1d937ed18008b60532a1ebfbfadd4f8b4a83",
    "filename": "Hakkan.java",
    "status": "modified",
    "additions": 6,
    "deletions": 1,
    "changes": 7,
    "blob_url": "https://github.com/Andi-IM/desktop-project/blob/b7c15fd2564917cf75d892449f5c403b52e58fd1/Hakkan.java",
    "raw_url": "https://github.com/Andi-IM/desktop-project/raw/b7c15fd2564917cf75d892449f5c403b52e58fd1/Hakkan.java",
    "contents_url": "https://api.github.com/repos/Andi-IM/desktop-project/contents/Hakkan.java?ref=b7c15fd2564917cf75d892449f5c403b52e58fd1",
    "patch": "@@ -1,7 +1,12 @@\n-public class Hakkan {\n+public class Hakkan implements GetItem{\n     private  static String nama = \"Hakkan\";\n \n     public static  String getNama(){\n         return nama;\n     }\n+\n+    @Override\n+    public void tampilkan(){\n+        System.out.println(getNama());\n+    }\n }"
  },
  {
    "sha": "e303a6d4395dabfd6d84adab0da088ae453ab048",
    "filename": "Minum.java",
    "status": "modified",
    "additions": 2,
    "deletions": 0,
    "changes": 2,
    "blob_url": "https://github.com/Andi-IM/desktop-project/blob/b7c15fd2564917cf75d892449f5c403b52e58fd1/Minum.java",
    "raw_url": "https://github.com/Andi-IM/desktop-project/raw/b7c15fd2564917cf75d892449f5c403b52e58fd1/Minum.java",
    "contents_url": "https://api.github.com/repos/Andi-IM/desktop-project/contents/Minum.java?ref=b7c15fd2564917cf75d892449f5c403b52e58fd1",
    "patch": "@@ -1,4 +1,6 @@\n+\n public class Minum {\n+    private Minum {() {}\n     public static void main(String[] args) {\n         System.out.println(\"Belajar Github\");\n         System.out.println();"
  },
  {
    "sha": "18bfa51df5979773eeb0576ac70677300e71c1fd",
    "filename": "Mulai.java",
    "status": "modified",
    "additions": 7,
    "deletions": 1,
    "changes": 8,
    "blob_url": "https://github.com/Andi-IM/desktop-project/blob/b7c15fd2564917cf75d892449f5c403b52e58fd1/Mulai.java",
    "raw_url": "https://github.com/Andi-IM/desktop-project/raw/b7c15fd2564917cf75d892449f5c403b52e58fd1/Mulai.java",
    "contents_url": "https://api.github.com/repos/Andi-IM/desktop-project/contents/Mulai.java?ref=b7c15fd2564917cf75d892449f5c403b52e58fd1",
    "patch": "@@ -1,8 +1,14 @@\n+\n public class Mulai {\n     public static void main(String[] args) {\n         System.out.println(\"Belajar Github\");\n         System.out.println();\n-        tampilkan(\"Hakkan\");\n+        // tampilkan(\"Hakkan\");\n+\n+        new Hakkan().tampilkan(); // cara singkat untuk memanggil objek\n+        \n+        Andi andi = new Andi();\n+        andi.tampilkan(); // memanggil interface untuk memanggil nama \"Andi\"\n     }\n \n     public static void tampilkan(String nama){"
  }
]
